build/lib/cegal/welltools/main.py
build/lib/cegal/welltools/plotting.py
build/lib/cegal/welltools/utilities.py
build/lib/cegal/welltools/wells.py
build/lib/tests/smoke.py
cegal/welltools/main.py
cegal/welltools/plotting.py
cegal/welltools/utilities.py
cegal/welltools/wells.py
tests/smoke.py
cegal_welltools-0.1.0.dist-info/LICENSE
cegal_welltools-0.1.0.dist-info/METADATA
cegal_welltools-0.1.0.dist-info/WHEEL
cegal_welltools-0.1.0.dist-info/top_level.txt
cegal_welltools-0.1.0.dist-info/RECORD
