Metadata-Version: 2.1
Name: cegal-welltools
Version: 0.1.0
Summary: Cegal AS-provided well log package
Home-page: https://github.com/cegaldev/cegaltools
Author: Hilde Haland
Author-email: hilde.tveit.haland@gmail.com
License: UNKNOWN
Platform: UNKNOWN
Classifier: Programming Language :: Python :: 3
Classifier: License :: OSI Approved :: BSD License
Classifier: Operating System :: OS Independent
Requires-Python: >=3.6
Requires-Dist: colour (>=0.1.5)
Requires-Dist: lasio (>=0.25.1)
Requires-Dist: numpy (>=1.18.0)
Requires-Dist: pandas (>=1.0.3)
Requires-Dist: plotly (>=4.6.0)
Requires-Dist: scikit-learn (>=0.22.1)
